agi/__init__.py
agi/_http.py
agi/_session_context.py
agi/_sse.py
agi/client.py
agi/exceptions.py
agi/py.typed
agi/resources/__init__.py
agi/resources/sessions.py
agi/types/__init__.py
agi/types/results.py
agi/types/sessions.py
agi/types/shared.py
agi_python-0.0.1.dist-info/licenses/LICENSE
agi_python-0.0.1.dist-info/METADATA
agi_python-0.0.1.dist-info/WHEEL
agi_python-0.0.1.dist-info/top_level.txt
agi_python-0.0.1.dist-info/RECORD
