Metadata-Version: 2.4
Name: agi-python
Version: 0.0.1
Summary: Official Python SDK for AGI.tech API
Author-email: AGI Inc <kaushik@theagi.company>
Maintainer-email: AGI Inc <kaushik@theagi.company>
License-Expression: MIT
Project-URL: Homepage, https://github.com/agi-inc/agi-python
Project-URL: Documentation, https://docs.agi.tech
Project-URL: Repository, https://github.com/agi-inc/agi-python
Project-URL: Issues, https://github.com/agi-inc/agi-python/issues
Project-URL: Changelog, https://github.com/agi-inc/agi-python/releases
Keywords: agi,automation,browser,ai,agent,api,sdk
Classifier: Development Status :: 5 - Production/Stable
Classifier: Intended Audience :: Developers
Classifier: Programming Language :: Python :: 3
Classifier: Programming Language :: Python :: 3.11
Classifier: Programming Language :: Python :: 3.12
Classifier: Programming Language :: Python :: 3.13
Classifier: Topic :: Software Development :: Libraries :: Python Modules
Classifier: Topic :: Internet :: WWW/HTTP
Classifier: Typing :: Typed
Requires-Python: >=3.11
License-File: LICENSE
Requires-Dist: httpx>=0.27.0
Requires-Dist: pydantic>=2.0.0
Requires-Dist: typing-extensions>=4.5.0
Provides-Extra: dev
Requires-Dist: pytest>=7.0.0; extra == "dev"
Requires-Dist: pytest-asyncio>=0.21.0; extra == "dev"
Requires-Dist: pytest-cov>=4.0.0; extra == "dev"
Requires-Dist: pytest-mock>=3.12.0; extra == "dev"
Requires-Dist: mypy>=1.0.0; extra == "dev"
Requires-Dist: ruff>=0.1.0; extra == "dev"
Requires-Dist: pre-commit>=3.0.0; extra == "dev"
Dynamic: license-file
